print_package/__init__.py
print_package/print_package.py
print_package-1.0.0.dist-info/LICENCE.txt
print_package-1.0.0.dist-info/METADATA
print_package-1.0.0.dist-info/WHEEL
print_package-1.0.0.dist-info/top_level.txt
print_package-1.0.0.dist-info/RECORD
