Metadata-Version: 2.1
Name: print_package
Version: 1.0.0
Summary: A simple Python package for printing messages.
Home-page: https://github.com/your_username/print_package
Author: Tanvir
Author-email: 2020tanvir1971@gmail.com
Classifier: Programming Language :: Python :: 3
Classifier: License :: OSI Approved :: MIT License
Classifier: Operating System :: OS Independent
License-File: LICENCE.txt
